{"frames": {

"abundantvessel.png":
{
	"frame": {"x":2,"y":1726,"w":300,"h":300},
	"rotated": false,
	"trimmed": false,
	"spriteSourceSize": {"x":0,"y":0,"w":300,"h":300},
	"sourceSize": {"w":300,"h":300},
	"pivot": {"x":0.5,"y":0.5}
},
"auctionhouse.png":
{
	"frame": {"x":304,"y":1726,"w":300,"h":300},
	"rotated": false,
	"trimmed": false,
	"spriteSourceSize": {"x":0,"y":0,"w":300,"h":300},
	"sourceSize": {"w":300,"h":300},
	"pivot": {"x":0.5,"y":0.5}
},
"basecamp.png":
{
	"frame": {"x":606,"y":1726,"w":300,"h":300},
	"rotated": false,
	"trimmed": false,
	"spriteSourceSize": {"x":0,"y":0,"w":300,"h":300},
	"sourceSize": {"w":300,"h":300},
	"pivot": {"x":0.5,"y":0.5}
},
"blackcard.png":
{
	"frame": {"x":2,"y":2,"w":550,"h":860},
	"rotated": false,
	"trimmed": false,
	"spriteSourceSize": {"x":0,"y":0,"w":550,"h":860},
	"sourceSize": {"w":550,"h":860},
	"pivot": {"x":0.5,"y":0.5}
},
"bluecard.png":
{
	"frame": {"x":554,"y":2,"w":550,"h":860},
	"rotated": false,
	"trimmed": false,
	"spriteSourceSize": {"x":0,"y":0,"w":550,"h":860},
	"sourceSize": {"w":550,"h":860},
	"pivot": {"x":0.5,"y":0.5}
},
"bluecard.psd":
{
	"frame": {"x":1106,"y":2,"w":550,"h":860},
	"rotated": false,
	"trimmed": false,
	"spriteSourceSize": {"x":0,"y":0,"w":550,"h":860},
	"sourceSize": {"w":550,"h":860},
	"pivot": {"x":0.5,"y":0.5}
},
"boarranch.png":
{
	"frame": {"x":908,"y":1726,"w":300,"h":300},
	"rotated": false,
	"trimmed": false,
	"spriteSourceSize": {"x":0,"y":0,"w":300,"h":300},
	"sourceSize": {"w":300,"h":300},
	"pivot": {"x":0.5,"y":0.5}
},
"build.png":
{
	"frame": {"x":1210,"y":1726,"w":300,"h":300},
	"rotated": false,
	"trimmed": false,
	"spriteSourceSize": {"x":0,"y":0,"w":300,"h":300},
	"sourceSize": {"w":300,"h":300},
	"pivot": {"x":0.5,"y":0.5}
},
"cave1.png":
{
	"frame": {"x":1512,"y":1726,"w":300,"h":300},
	"rotated": false,
	"trimmed": false,
	"spriteSourceSize": {"x":0,"y":0,"w":300,"h":300},
	"sourceSize": {"w":300,"h":300},
	"pivot": {"x":0.5,"y":0.5}
},
"charcoalfurnace.png":
{
	"frame": {"x":1658,"y":2,"w":300,"h":300},
	"rotated": false,
	"trimmed": false,
	"spriteSourceSize": {"x":0,"y":0,"w":300,"h":300},
	"sourceSize": {"w":300,"h":300},
	"pivot": {"x":0.5,"y":0.5}
},
"cobaltmine.png":
{
	"frame": {"x":1658,"y":304,"w":300,"h":300},
	"rotated": false,
	"trimmed": false,
	"spriteSourceSize": {"x":0,"y":0,"w":300,"h":300},
	"sourceSize": {"w":300,"h":300},
	"pivot": {"x":0.5,"y":0.5}
},
"demolition.png":
{
	"frame": {"x":1658,"y":606,"w":300,"h":300},
	"rotated": false,
	"trimmed": false,
	"spriteSourceSize": {"x":0,"y":0,"w":300,"h":300},
	"sourceSize": {"w":300,"h":300},
	"pivot": {"x":0.5,"y":0.5}
},
"desert.png":
{
	"frame": {"x":1658,"y":1512,"w":300,"h":150},
	"rotated": false,
	"trimmed": false,
	"spriteSourceSize": {"x":0,"y":0,"w":300,"h":150},
	"sourceSize": {"w":300,"h":150},
	"pivot": {"x":0.5,"y":0.5}
},
"downarrow.png":
{
	"frame": {"x":1658,"y":1664,"w":140,"h":20},
	"rotated": false,
	"trimmed": false,
	"spriteSourceSize": {"x":0,"y":0,"w":140,"h":20},
	"sourceSize": {"w":140,"h":20},
	"pivot": {"x":0.5,"y":0.5}
},
"envoyharbor.png":
{
	"frame": {"x":1658,"y":908,"w":300,"h":300},
	"rotated": false,
	"trimmed": false,
	"spriteSourceSize": {"x":0,"y":0,"w":300,"h":300},
	"sourceSize": {"w":300,"h":300},
	"pivot": {"x":0.5,"y":0.5}
},
"firecrew.png":
{
	"frame": {"x":1658,"y":1210,"w":300,"h":300},
	"rotated": false,
	"trimmed": false,
	"spriteSourceSize": {"x":0,"y":0,"w":300,"h":300},
	"sourceSize": {"w":300,"h":300},
	"pivot": {"x":0.5,"y":0.5}
},
"greencard.png":
{
	"frame": {"x":2,"y":864,"w":550,"h":860},
	"rotated": false,
	"trimmed": false,
	"spriteSourceSize": {"x":0,"y":0,"w":550,"h":860},
	"sourceSize": {"w":550,"h":860},
	"pivot": {"x":0.5,"y":0.5}
},
"orangecard.png":
{
	"frame": {"x":554,"y":864,"w":550,"h":860},
	"rotated": false,
	"trimmed": false,
	"spriteSourceSize": {"x":0,"y":0,"w":550,"h":860},
	"sourceSize": {"w":550,"h":860},
	"pivot": {"x":0.5,"y":0.5}
},
"redcard.png":
{
	"frame": {"x":1106,"y":864,"w":550,"h":860},
	"rotated": false,
	"trimmed": false,
	"spriteSourceSize": {"x":0,"y":0,"w":550,"h":860},
	"sourceSize": {"w":550,"h":860},
	"pivot": {"x":0.5,"y":0.5}
},
"tinydesert.png":
{
	"frame": {"x":1658,"y":1686,"w":33,"h":18},
	"rotated": false,
	"trimmed": false,
	"spriteSourceSize": {"x":0,"y":0,"w":33,"h":18},
	"sourceSize": {"w":33,"h":18},
	"pivot": {"x":0.5,"y":0.5}
},
"tinyforested.png":
{
	"frame": {"x":1693,"y":1686,"w":33,"h":18},
	"rotated": false,
	"trimmed": false,
	"spriteSourceSize": {"x":0,"y":0,"w":33,"h":18},
	"sourceSize": {"w":33,"h":18},
	"pivot": {"x":0.5,"y":0.5}
},
"tinygrassy.png":
{
	"frame": {"x":1728,"y":1686,"w":33,"h":18},
	"rotated": false,
	"trimmed": false,
	"spriteSourceSize": {"x":0,"y":0,"w":33,"h":18},
	"sourceSize": {"w":33,"h":18},
	"pivot": {"x":0.5,"y":0.5}
},
"tinyrocky.png":
{
	"frame": {"x":1763,"y":1686,"w":33,"h":18},
	"rotated": false,
	"trimmed": false,
	"spriteSourceSize": {"x":0,"y":0,"w":33,"h":18},
	"sourceSize": {"w":33,"h":18},
	"pivot": {"x":0.5,"y":0.5}
},
"tinysea.png":
{
	"frame": {"x":1814,"y":1706,"w":33,"h":18},
	"rotated": false,
	"trimmed": false,
	"spriteSourceSize": {"x":0,"y":0,"w":33,"h":18},
	"sourceSize": {"w":33,"h":18},
	"pivot": {"x":0.5,"y":0.5}
},
"tinyshore.png":
{
	"frame": {"x":1814,"y":1686,"w":34,"h":18},
	"rotated": false,
	"trimmed": false,
	"spriteSourceSize": {"x":0,"y":0,"w":34,"h":18},
	"sourceSize": {"w":34,"h":18},
	"pivot": {"x":0.5,"y":0.5}
},
"uparrow.png":
{
	"frame": {"x":1800,"y":1664,"w":140,"h":20},
	"rotated": false,
	"trimmed": false,
	"spriteSourceSize": {"x":0,"y":0,"w":140,"h":20},
	"sourceSize": {"w":140,"h":20},
	"pivot": {"x":0.5,"y":0.5}
}},
"meta": {
	"app": "http://www.codeandweb.com/texturepacker",
	"version": "1.0",
	"image": "images-0.png",
	"format": "RGBA8888",
	"size": {"w":1960,"h":2028},
	"scale": "1",
	"smartupdate": "$TexturePacker:SmartUpdate:cfb3240462009c6b9123c77edaeeda02:bc3133292ce586437bf6f7b04516f3aa:4b437caca69fd16d5f6bf05828e98a30$"
}
}
